aprl/__init__.py
aprl/config.py
aprl/core.py
aprl/queue.py
tests/__init__.py
tests/test_config.py
tests/test_core.py
tests/test_queue.py
apirl-0.1.0.dist-info/LICENSE
apirl-0.1.0.dist-info/METADATA
apirl-0.1.0.dist-info/WHEEL
apirl-0.1.0.dist-info/top_level.txt
apirl-0.1.0.dist-info/RECORD
