Metadata-Version: 2.1
Name: apirl
Version: 0.1.0
Summary: A Python package to manage API rate limits by automatically queuing and pacing API requests.
Home-page: https://github.com/mixter3011/aprl.git
Author: Sabyasachi
Author-email: sabychakraborty08@gmail.com
Classifier: Programming Language :: Python :: 3
Classifier: License :: OSI Approved :: MIT License
Classifier: Operating System :: OS Independent
Requires-Python: >=3.6
License-File: LICENSE
Requires-Dist: certifi
Requires-Dist: python-dotenv
Provides-Extra: dev
Requires-Dist: pytest ; extra == 'dev'
